pyshover/__init__.py
pyshover/cli.py
pyshover/pushover.py
pyshover-0.0.7.dist-info/METADATA
pyshover-0.0.7.dist-info/WHEEL
pyshover-0.0.7.dist-info/entry_points.txt
pyshover-0.0.7.dist-info/top_level.txt
pyshover-0.0.7.dist-info/RECORD
