Metadata-Version: 2.4
Name: pyshover
Version: 0.0.7
Summary: Quickly send Pushover messages
Author: Scott Walsh
Author-email: scott@invisiblethreat.ca
Maintainer: Scott Walsh
Maintainer-email: scott@invisiblethreat.ca
Project-URL: homepage, https://github.com/invisiblethreat/pyshover
Project-URL: documentation, https://github.com/invisiblethreat/pyshover/blob/main/README.md
Project-URL: repository, https://github.com/invisiblethreat/pyshover
Keywords: pushover,notifications
Classifier: Development Status :: 4 - Beta
Classifier: Programming Language :: Python
Requires-Python: >=3.7
